shelper/__init__.py
shelper/interrupt.py
shelper/progress.py
shelper/shell.py
shelper-0.1.4.dist-info/METADATA
shelper-0.1.4.dist-info/WHEEL
shelper-0.1.4.dist-info/RECORD
