Metadata-Version: 2.3
Name: shelper
Version: 0.1.4
Summary: The shell helper
Author: Danny Stewart
Author-email: danny@stewart.cc
Requires-Python: >=3.12
Classifier: Programming Language :: Python :: 3
Classifier: Programming Language :: Python :: 3.12
Classifier: Programming Language :: Python :: 3.13
Requires-Dist: halo (>=0.0.31,<0.0.32)
Requires-Dist: logician (>=0.3.2)
Requires-Dist: textparse (>=0.1.2)
